geniuses/__init__.py
geniuses/__main__.py
geniuses/_version.py
geniuses/client.py
geniuses/model.py
geniuses-0.0.1.dist-info/LICENSE
geniuses-0.0.1.dist-info/METADATA
geniuses-0.0.1.dist-info/WHEEL
geniuses-0.0.1.dist-info/top_level.txt
geniuses-0.0.1.dist-info/RECORD
