Metadata-Version: 2.1
Name: geniuses
Version: 0.0.1
Summary: Genius REST API Client
Home-page: https://github.com/aksakalli/geniuses
Author: Can Güney Aksakalli
Author-email: cgaksakalli@gmail.com
License: Apache 2.0
Platform: UNKNOWN
Classifier: Development Status :: 4 - Beta
Classifier: Intended Audience :: Developers
Classifier: Natural Language :: English
Classifier: License :: OSI Approved :: Apache Software License
Classifier: Programming Language :: Python
Classifier: Programming Language :: Python :: 3.6
Classifier: Programming Language :: Python :: 3.7
Classifier: Programming Language :: Python :: 3.8
Classifier: Programming Language :: Python :: Implementation :: CPython
Classifier: Programming Language :: Python :: Implementation :: PyPy
Requires-Python: >=3.6, <4
Requires-Dist: requests
Requires-Dist: beautifulsoup4
